README.md
setup.py
gomatic/__init__.py
gomatic/fake.py
gomatic/go_cd_configurator.py
gomatic/mixins.py
gomatic/xml_operations.py
gomatic.egg-info/PKG-INFO
gomatic.egg-info/SOURCES.txt
gomatic.egg-info/dependency_links.txt
gomatic.egg-info/not-zip-safe
gomatic.egg-info/requires.txt
gomatic.egg-info/top_level.txt
gomatic/gocd/__init__.py
gomatic/gocd/agents.py
gomatic/gocd/artifacts.py
gomatic/gocd/authorization.py
gomatic/gocd/config_repos.py
gomatic/gocd/elastic.py
gomatic/gocd/generic.py
gomatic/gocd/materials.py
gomatic/gocd/pipelines.py
gomatic/gocd/repositories.py
gomatic/gocd/security.py
gomatic/gocd/tasks.py