Metadata-Version: 1.0
Name: gomatic
Version: 0.5.10
Summary: API for configuring GoCD
Home-page: https://github.com/gocd-contrib/gomatic
Author: The Gomatic Maintainers
Author-email: UNKNOWN
License: MIT
Platform: UNKNOWN
